djangorestframework_mcp/__init__.py
djangorestframework_mcp/apps.py
djangorestframework_mcp/decorators.py
djangorestframework_mcp/registry.py
djangorestframework_mcp/schema.py
djangorestframework_mcp/settings.py
djangorestframework_mcp/test.py
djangorestframework_mcp/types.py
djangorestframework_mcp/urls.py
djangorestframework_mcp/views.py
django_rest_framework_mcp-0.1.0a3.dist-info/METADATA
django_rest_framework_mcp-0.1.0a3.dist-info/WHEEL
django_rest_framework_mcp-0.1.0a3.dist-info/top_level.txt
django_rest_framework_mcp-0.1.0a3.dist-info/RECORD
